[
  {
    "offense": 33.74468854552204,
    "defense": 18.11098588688208,
    "overall": 51.855674432404115,
    "team": {
      "id": 80,
      "name": "Brown"
    }
  },
  {
    "offense": 29.387308620907994,
    "defense": 20.187560903947308,
    "overall": 49.5748695248553,
    "team": {
      "id": 392,
      "name": "Maryland"
    }
  },
  {
    "offense": 29.186666991932825,
    "defense": 19.65278070242689,
    "overall": 48.83944769435972,
    "team": {
      "id": 688,
      "name": "Syracuse"
    }
  },
  {
    "offense": 31.357766612764635,
    "defense": 17.16263037391024,
    "overall": 48.520396986674875,
    "team": {
      "id": 457,
      "name": "North Carolina"
    }
  },
  {
    "offense": 28.382608012158112,
    "defense": 20.06448466134629,
    "overall": 48.4470926735044,
    "team": {
      "id": 513,
      "name": "Notre Dame"
    }
  },
  {
    "offense": 29.220825758007454,
    "defense": 19.1248985429304,
    "overall": 48.34572430093785,
    "team": {
      "id": 813,
      "name": "Yale"
    }
  },
  {
    "offense": 30.354073884624366,
    "defense": 17.68033547183488,
    "overall": 48.03440935645925,
    "team": {
      "id": 183,
      "name": "Denver"
    }
  },
  {
    "offense": 30.516020415445546,
    "defense": 17.213205670023285,
    "overall": 47.72922608546883,
    "team": {
      "id": 193,
      "name": "Duke"
    }
  },
  {
    "offense": 28.269386908067908,
    "defense": 18.919821097536985,
    "overall": 47.1892080056049,
    "team": {
      "id": 369,
      "name": "Loyola Maryland"
    }
  },
  {
    "offense": 30.663907406431782,
    "defense": 16.362110779937293,
    "overall": 47.02601818636907,
    "team": {
      "id": 739,
      "name": "Villanova"
    }
  },
  {
    "offense": 29.822848790930685,
    "defense": 17.01677942782583,
    "overall": 46.839628218756516,
    "team": {
      "id": 14,
      "name": "Albany (NY)"
    }
  },
  {
    "offense": 29.959138451932336,
    "defense": 16.836488517136228,
    "overall": 46.795626969068564,
    "team": {
      "id": 322,
      "name": "Johns Hopkins"
    }
  },
  {
    "offense": 26.857508765408262,
    "defense": 19.836661533271844,
    "overall": 46.694170298680106,
    "team": {
      "id": 726,
      "name": "Navy"
    }
  },
  {
    "offense": 27.586187991932,
    "defense": 19.04197648561125,
    "overall": 46.62816447754325,
    "team": {
      "id": 711,
      "name": "Towson"
    }
  },
  {
    "offense": 28.81033425834046,
    "defense": 17.658967095978202,
    "overall": 46.46930135431866,
    "team": {
      "id": 275,
      "name": "Harvard"
    }
  },
  {
    "offense": 28.717044889111623,
    "defense": 17.73320996603191,
    "overall": 46.450254855143534,
    "team": {
      "id": 683,
      "name": "Stony Brook"
    }
  },
  {
    "offense": 29.267976596360494,
    "defense": 16.81707433527292,
    "overall": 46.08505093163342,
    "team": {
      "id": 539,
      "name": "Penn St."
    }
  },
  {
    "offense": 27.93825774859159,
    "defense": 17.982294764202667,
    "overall": 45.92055251279426,
    "team": {
      "id": 725,
      "name": "Army West Point"
    }
  },
  {
    "offense": 28.84391136397837,
    "defense": 16.796579980927977,
    "overall": 45.64049134490635,
    "team": {
      "id": 587,
      "name": "Rutgers"
    }
  },
  {
    "offense": 26.300198090262082,
    "defense": 19.237015227534688,
    "overall": 45.53721331779677,
    "team": {
      "id": 387,
      "name": "Marquette"
    }
  },
  {
    "offense": 27.657973011720927,
    "defense": 17.670262103237302,
    "overall": 45.32823511495823,
    "team": {
      "id": 83,
      "name": "Bucknell"
    }
  },
  {
    "offense": 27.921296377309204,
    "defense": 17.156892289163935,
    "overall": 45.07818866647314,
    "team": {
      "id": 746,
      "name": "Virginia"
    }
  },
  {
    "offense": 26.98906973187587,
    "defense": 18.026980651532735,
    "overall": 45.016050383408604,
    "team": {
      "id": 81,
      "name": "Bryant"
    }
  },
  {
    "offense": 26.982005272495993,
    "defense": 17.99853433087215,
    "overall": 44.98053960336814,
    "team": {
      "id": 540,
      "name": "Penn"
    }
  },
  {
    "offense": 27.503756458067457,
    "defense": 17.228059111209877,
    "overall": 44.73181556927733,
    "team": {
      "id": 606,
      "name": "Saint Joseph's"
    }
  },
  {
    "offense": 26.665379138800507,
    "defense": 17.958998096281498,
    "overall": 44.62437723508201,
    "team": {
      "id": 518,
      "name": "Ohio St."
    }
  },
  {
    "offense": 25.996791813372482,
    "defense": 18.252249129716574,
    "overall": 44.24904094308906,
    "team": {
      "id": 400,
      "name": "Massachusetts"
    }
  },
  {
    "offense": 26.388780435129412,
    "defense": 17.6524508087411,
    "overall": 44.04123124387051,
    "team": {
      "id": 283,
      "name": "Hofstra"
    }
  },
  {
    "offense": 26.35466913388514,
    "defense": 17.523695312837255,
    "overall": 43.878364446722394,
    "team": {
      "id": 167,
      "name": "Cornell"
    }
  },
  {
    "offense": 26.460758143463874,
    "defense": 17.334203602993405,
    "overall": 43.794961746457275,
    "team": {
      "id": 220,
      "name": "Fairfield"
    }
  },
  {
    "offense": 25.96892515202447,
    "defense": 17.642776974486456,
    "overall": 43.61170212651093,
    "team": {
      "id": 191,
      "name": "Drexel"
    }
  },
  {
    "offense": 25.914015004415084,
    "defense": 17.443967373873395,
    "overall": 43.35798237828848,
    "team": {
      "id": 721,
      "name": "Air Force"
    }
  },
  {
    "offense": 26.968324767455975,
    "defense": 16.041768443073593,
    "overall": 43.01009321052957,
    "team": {
      "id": 554,
      "name": "Princeton"
    }
  },
  {
    "offense": 26.193056235999126,
    "defense": 16.779054592333573,
    "overall": 42.9721108283327,
    "team": {
      "id": 562,
      "name": "Quinnipiac"
    }
  },
  {
    "offense": 24.36994405406251,
    "defense": 18.594860485191685,
    "overall": 42.964804539254196,
    "team": {
      "id": 575,
      "name": "Richmond"
    }
  },
  {
    "offense": 26.85172018621423,
    "defense": 15.742204039387147,
    "overall": 42.59392422560138,
    "team": {
      "id": 272,
      "name": "Hartford"
    }
  },
  {
    "offense": 25.734677903099154,
    "defense": 16.726192911130706,
    "overall": 42.460870814229864,
    "team": {
      "id": 68,
      "name": "Boston U."
    }
  },
  {
    "offense": 26.87055674678068,
    "defense": 15.527054974427791,
    "overall": 42.39761172120847,
    "team": {
      "id": 352,
      "name": "Lehigh"
    }
  },
  {
    "offense": 27.48591631178975,
    "defense": 14.895920409149639,
    "overall": 42.38183672093939,
    "team": {
      "id": 738,
      "name": "Vermont"
    }
  },
  {
    "offense": 26.056042760366726,
    "defense": 16.24579341358698,
    "overall": 42.3018361739537,
    "team": {
      "id": 556,
      "name": "Providence"
    }
  },
  {
    "offense": 26.964479751996556,
    "defense": 14.77608538900025,
    "overall": 41.74056514099681,
    "team": {
      "id": 19651,
      "name": "High Point"
    }
  },
  {
    "offense": 25.387775561581737,
    "defense": 16.277567111783714,
    "overall": 41.66534267336545,
    "team": {
      "id": 282,
      "name": "Hobart and William Colleges"
    }
  },
  {
    "offense": 27.18196429266293,
    "defense": 14.213350468838424,
    "overall": 41.39531476150135,
    "team": {
      "id": 579,
      "name": "Robert Morris"
    }
  },
  {
    "offense": 26.23720127518084,
    "defense": 15.072621486263827,
    "overall": 41.309822761444664,
    "team": {
      "id": 418,
      "name": "Michigan"
    }
  },
  {
    "offense": 24.73072231524847,
    "defense": 16.57764156258682,
    "overall": 41.30836387783529,
    "team": {
      "id": 386,
      "name": "Marist"
    }
  },
  {
    "offense": 25.65978127440919,
    "defense": 15.513679306120057,
    "overall": 41.17346058052925,
    "team": {
      "id": 285,
      "name": "Holy Cross"
    }
  },
  {
    "offense": 24.60773637329923,
    "defense": 16.414010924665508,
    "overall": 41.02174729796474,
    "team": {
      "id": 251,
      "name": "Georgetown"
    }
  },
  {
    "offense": 24.63679175177457,
    "defense": 16.18073096968993,
    "overall": 40.8175227214645,
    "team": {
      "id": 52,
      "name": "Bellarmine"
    }
  },
  {
    "offense": 24.523200588627326,
    "defense": 16.020623449183525,
    "overall": 40.54382403781085,
    "team": {
      "id": 153,
      "name": "Colgate"
    }
  },
  {
    "offense": 25.335580631791224,
    "defense": 15.028036438195862,
    "overall": 40.363617069987086,
    "team": {
      "id": 450,
      "name": "Mt. St. Mary's"
    }
  },
  {
    "offense": 24.415613928709345,
    "defense": 15.836952583808635,
    "overall": 40.25256651251798,
    "team": {
      "id": 180,
      "name": "Delaware"
    }
  },
  {
    "offense": 25.409812516526024,
    "defense": 14.834144279091575,
    "overall": 40.2439567956176,
    "team": {
      "id": 391,
      "name": "UMBC"
    }
  },
  {
    "offense": 25.866175730674634,
    "defense": 14.228337662691972,
    "overall": 40.094513393366604,
    "team": {
      "id": 62,
      "name": "Binghamton"
    }
  },
  {
    "offense": 24.157687849599146,
    "defense": 15.732008279627522,
    "overall": 39.889696129226664,
    "team": {
      "id": 439,
      "name": "Monmouth"
    }
  },
  {
    "offense": 24.612274814405833,
    "defense": 14.82912976799049,
    "overall": 39.44140458239632,
    "team": {
      "id": 116,
      "name": "Canisius"
    }
  },
  {
    "offense": 24.848031054542613,
    "defense": 14.329677189811264,
    "overall": 39.17770824435388,
    "team": {
      "id": 406,
      "name": "Mercer"
    }
  },
  {
    "offense": 25.204940143717767,
    "defense": 13.837668452866318,
    "overall": 39.04260859658409,
    "team": {
      "id": 603,
      "name": "St. John's (NY)"
    }
  },
  {
    "offense": 23.937113029979688,
    "defense": 14.681086072955278,
    "overall": 38.618199102934966,
    "team": {
      "id": 244,
      "name": "Furman"
    }
  },
  {
    "offense": 22.697077941314866,
    "defense": 15.64588681689127,
    "overall": 38.342964758206136,
    "team": {
      "id": 184,
      "name": "Detroit"
    }
  },
  {
    "offense": 24.345563140497575,
    "defense": 13.777430068511958,
    "overall": 38.122993209009536,
    "team": {
      "id": 590,
      "name": "Sacred Heart"
    }
  },
  {
    "offense": 23.80733861346276,
    "defense": 14.059634532428781,
    "overall": 37.86697314589154,
    "team": {
      "id": 342,
      "name": "Lafayette"
    }
  },
  {
    "offense": 24.475875450699217,
    "defense": 13.26909857061056,
    "overall": 37.74497402130977,
    "team": {
      "id": 639,
      "name": "Siena"
    }
  },
  {
    "offense": 23.498016932927094,
    "defense": 14.024751807503458,
    "overall": 37.52276874043055,
    "team": {
      "id": 368,
      "name": "UMass Lowell"
    }
  },
  {
    "offense": 23.439613691527185,
    "defense": 13.8300410451888,
    "overall": 37.269654736715985,
    "team": {
      "id": 316,
      "name": "Jacksonville"
    }
  },
  {
    "offense": 22.237458394522577,
    "defense": 14.28387477015737,
    "overall": 36.521333164679945,
    "team": {
      "id": 172,
      "name": "Dartmouth"
    }
  },
  {
    "offense": 22.402204504840906,
    "defense": 13.61011307171535,
    "overall": 36.012317576556256,
    "team": {
      "id": 748,
      "name": "Wagner"
    }
  },
  {
    "offense": 22.18878543944038,
    "defense": 12.939538323237677,
    "overall": 35.12832376267806,
    "team": {
      "id": 381,
      "name": "Manhattan"
    }
  },
  {
    "offense": 21.0262681043553,
    "defense": 11.153920879343936,
    "overall": 32.18018898369924,
    "team": {
      "id": 471,
      "name": "NJIT"
    }
  },
  {
    "offense": 20.597795440253957,
    "defense": 10.491336194288499,
    "overall": 31.089131634542454,
    "team": {
      "id": 741,
      "name": "VMI"
    }
  },
  {
    "offense": 16.050724663156995,
    "defense": 0.0,
    "overall": 16.050724663156995,
    "team": {
      "id": 270,
      "name": "Hampton"
    }
  }
]